README.md
setup.cfg
setup.py
jw_pylib.egg-info/PKG-INFO
jw_pylib.egg-info/SOURCES.txt
jw_pylib.egg-info/dependency_links.txt
jw_pylib.egg-info/requires.txt
jw_pylib.egg-info/top_level.txt
pylib/__init__.py
pylib/crypto.py
pylib/datetime.py
pylib/dfa.py
pylib/email.py
pylib/fabfile.py
pylib/image.py
pylib/log.py
pylib/page.py
pylib/profile.py
pylib/security.py
pylib/session.py
pylib/sms.py
pylib/string.py
pylib/type.py
pylib/version.py
pylib/zto.py
pylib/alipay/__init__.py
pylib/aliyun/__init__.py
pylib/aliyun/oss.py
pylib/facepp/__init__.py
pylib/facepp/api.py
pylib/form/__init__.py
pylib/form/field.py
pylib/form/validator.py
pylib/mob/__init__.py
pylib/pingpp/__init__.py
pylib/tornado/__init__.py
pylib/tornado/signal.py
pylib/umeng/__init__.py
pylib/umeng/message.py