Metadata-Version: 2.1
Name: jw-pylib
Version: 1.0.0
Summary: Some useful python utils
Home-page: https://github.com/jaggerwang/jw-pylib
Author: Jagger Wang
Author-email: jaggerwang@gmail.com
License: MIT
Project-URL: Bug Reports, https://github.com/jaggerwang/jw-pylib/issues
Project-URL: Source, https://github.com/jaggerwang/jw-pylib
Keywords: utils
Platform: UNKNOWN
Classifier: License :: OSI Approved :: MIT License
Requires-Python: >=3
Provides-Extra: test
Provides-Extra: dev
